[
  {
    "id": 1,
    "title": "فتح الباري",
    "author": "ابن حجر العسقلاني",
    "description": "شرح صحيح البخاري",
    "chapters": [
      {
        "title": "المقدمة",
        "content": "هذا هو نص المقدمة..."
      }
    ]
  }
]
,
  {
    "id": 2,
    "title": "صحيح مسلم",
    "author": "بن حجر العسقلاني",
    "description": "أحد كتب الحديث النبوي",
    "chapters": [
      {
        "title": "كتاب الإيمان",
        "content": "هذا هو نص كتاب الإيمان..."
      }
    ]
  },
  {
    "id": 3,
    "title": "رياض الصالحين",
    "author": "النووي",
    "description": "مجموعة من الأحاديث النبوية الشريفة",
    "chapters": [
      {
        "title": "كتاب الطهارة",
        "content": "هذا هو نص كتاب الطهارة..."
      }
    ]
  }
